sells_application/__init__.py
sells_application/discounts.py
sells_application/exeptions.py
sells_application/prices.py
sells_application/sells_control.py
sells_application/taxes.py
sells_application-0.1.0.dist-info/licenses/LICENCE
tests/__init__.py
tests/test_application_sells.py
sells_application-0.1.0.dist-info/METADATA
sells_application-0.1.0.dist-info/WHEEL
sells_application-0.1.0.dist-info/top_level.txt
sells_application-0.1.0.dist-info/RECORD
